glass/camb.py
glass_camb-2023.2.dist-info/LICENSE
glass_camb-2023.2.dist-info/METADATA
glass_camb-2023.2.dist-info/WHEEL
glass_camb-2023.2.dist-info/top_level.txt
glass_camb-2023.2.dist-info/RECORD
